sphinx_astropy/__init__.py
sphinx_astropy/version.py
sphinx_astropy/conf/__init__.py
sphinx_astropy/conf/v1.py
sphinx_astropy/conf/v2.py
sphinx_astropy/ext/__init__.py
sphinx_astropy/ext/changelog_links.py
sphinx_astropy/ext/edit_on_github.py
sphinx_astropy/ext/generate_config.py
sphinx_astropy/ext/intersphinx_toggle.py
sphinx_astropy/ext/missing_static.py
sphinx_astropy/local/python3_local_links.inv
sphinx_astropy/local/python3_local_links.txt
sphinx_astropy/tests/__init__.py
sphinx_astropy/tests/test_conf_v1.py
sphinx_astropy/tests/test_conf_v2.py
sphinx_astropy-1.10.dist-info/licenses/LICENSE.rst
sphinx_astropy-1.10.dist-info/METADATA
sphinx_astropy-1.10.dist-info/WHEEL
sphinx_astropy-1.10.dist-info/top_level.txt
sphinx_astropy-1.10.dist-info/RECORD
