Metadata-Version: 2.4
Name: sphinx-astropy
Version: 1.10
Summary: Sphinx extensions and configuration specific to the Astropy project
Home-page: https://github.com/astropy/sphinx-astropy
Author: The Astropy Developers
Author-email: astropy.team@gmail.com
License: BSD
Classifier: Intended Audience :: Developers
Classifier: Programming Language :: Python
Classifier: Programming Language :: Python :: 3
Classifier: Operating System :: OS Independent
Classifier: License :: OSI Approved :: BSD License
Requires-Python: >=3.9
License-File: LICENSE.rst
Requires-Dist: packaging
Requires-Dist: sphinx>=4.0.0
Requires-Dist: astropy-sphinx-theme
Requires-Dist: numpydoc
Requires-Dist: sphinx-automodapi
Requires-Dist: sphinx-gallery
Requires-Dist: sphinxcontrib-jquery
Requires-Dist: pillow
Requires-Dist: pytest-doctestplus>=0.11
Provides-Extra: confv2
Requires-Dist: pydata-sphinx-theme; extra == "confv2"
Requires-Dist: sphinx-copybutton; extra == "confv2"
Provides-Extra: all
Requires-Dist: astropy; extra == "all"
Provides-Extra: tests
Requires-Dist: pytest; extra == "tests"
Dynamic: license-file
